flanders-0.3.3.dist-info/METADATA
flanders-0.3.3.dist-info/WHEEL
flanders/__init__.py
flanders/flanders.cpython-314-darwin.so
flanders-0.3.3.dist-info/RECORD
