Metadata-Version: 2.4
Name: flanders
Version: 0.3.3
Author: Radovan Bast <bast@users.noreply.github.com>
Author-email: Radovan Bast <bast@users.noreply.github.com>
